{
  "strategy_id": "usdchf_weekly_volatility_mean_reversion",
  "code": "def generate_signals(df, params):\n    import pandas as pd\n    import numpy as np\n    \n    # Parameters\n    decline_threshold = params['decline_threshold']  # e.g., -0.02\n    holding_period = params['holding_period']        # weeks\n    vol_lookback = params['vol_lookback']            # e.g., 10\n    \n    # Compute weekly returns\n    df['return'] = df['close'].pct_change()\n    \n    # Compute ATR (weekly)\n    df['high_low'] = df['high'] - df['low']\n    df['atr'] = df['high_low'].rolling(window=vol_lookback).mean()\n    df['atr_median'] = df['atr'].rolling(window=vol_lookback*2).median()\n    \n    # Entry condition: sharp decline and elevated volatility\n    df['entry'] = (df['return'] < decline_threshold) & (df['atr'] > df['atr_median'])\n    \n    # Generate signals: 1 for long on entry bar, 0 otherwise\n    df['signal'] = 0\n    entry_indices = df[df['entry']].index\n    for idx in entry_indices:\n        # Find the index of the bar after entry (next week open)\n        loc = df.index.get_loc(idx)\n        if loc + 1 < len(df):\n            df.iloc[loc + 1, df.columns.get_loc('signal')] = 1\n    \n    # Exit after holding_period weeks or trailing stop\n    df['position'] = 0\n    in_position = False\n    entry_price = 0\n    bars_held = 0\n    exit_bar = None\n    for i in range(len(df)):\n        if df['signal'].iloc[i] == 1 and not in_position:\n            in_position = True\n            entry_price = df['close'].iloc[i]\n            bars_held = 0\n            exit_bar = i + holding_period\n        if in_position:\n            # Trailing stop: exit if close drops below entry_price - 2*ATR\n            if df['close'].iloc[i] < entry_price - 2 * df['atr'].iloc[i]:\n                df.iloc[i, df.columns.get_loc('position')] = 0\n                in_position = False\n            elif i >= exit_bar:\n                df.iloc[i, df.columns.get_loc('position')] = -1  # exit signal\n                in_position = False\n            else:\n                df.iloc[i, df.columns.get_loc('position')] = 1\n    \n    # Final signal: position held (1 for long, -1 for exit, 0 otherwise)\n    # The validator expects a column 'signal' with 1 for entry, 0 otherwise.\n    # We'll use the 'position' column to create a binary entry signal at the start of each trade.\n    # Simpler: just use the entry signal as generated above.\n    df['final_signal'] = df['signal']\n    return df['final_signal']",
  "param_grid": {
    "decline_threshold": [
      -0.015,
      -0.02,
      -0.025
    ],
    "holding_period": [
      2,
      3,
      4
    ],
    "vol_lookback": [
      10,
      15,
      20
    ]
  },
  "rationale": "After sharp weekly declines in USD/CHF (CHF strengthening) accompanied by elevated volatility, contrarian buying emerges from profit-taking by speculators and potential SNB intervention, leading to a short-term reversal.",
  "self_critique": {
    "why_this_might_be_noise": "Sharp declines in safe-haven pairs can persist during sustained risk-off episodes; the strategy may fail in prolonged crises where CHF continues to strengthen.",
    "what_would_disprove_this": "If during a period of global financial stress (e.g., 2008) the strategy suffers consecutive losses as USD/CHF keeps falling without reversal.",
    "similar_already_rejected": [
      "gold_weekly_consecutive_reversal"
    ]
  },
  "instrument": "USD_CHF"
}